pywhisper/__init__.py
pywhisper/__main__.py
pywhisper/audio.py
pywhisper/decoding.py
pywhisper/model.py
pywhisper/tokenizer.py
pywhisper/transcribe.py
pywhisper/utils.py
pywhisper/assets/mel_filters.npz
pywhisper/assets/gpt2/merges.txt
pywhisper/assets/gpt2/special_tokens_map.json
pywhisper/assets/gpt2/tokenizer_config.json
pywhisper/assets/gpt2/vocab.json
pywhisper/assets/multilingual/added_tokens.json
pywhisper/assets/multilingual/merges.txt
pywhisper/assets/multilingual/special_tokens_map.json
pywhisper/assets/multilingual/tokenizer_config.json
pywhisper/assets/multilingual/vocab.json
pywhisper/normalizers/__init__.py
pywhisper/normalizers/basic.py
pywhisper/normalizers/english.json
pywhisper/normalizers/english.py
pywhisper-1.0.6.dist-info/LICENSE
pywhisper-1.0.6.dist-info/METADATA
pywhisper-1.0.6.dist-info/WHEEL
pywhisper-1.0.6.dist-info/entry_points.txt
pywhisper-1.0.6.dist-info/top_level.txt
pywhisper-1.0.6.dist-info/RECORD
