Metadata-Version: 2.1
Name: pywhisper
Version: 1.0.6
Summary: openai/whisper speech to text model + extra features
Home-page: https://github.com/fcakyon/pywhisper
Author: fcakyon
License: MIT
Keywords: machine-learning,deep-learning,ml,pytorch,speech-to-text,speech,text,nlp,natural-language-processing,openai,whisper
Classifier: License :: OSI Approved :: MIT License
Classifier: Operating System :: OS Independent
Classifier: Intended Audience :: Developers
Classifier: Intended Audience :: Science/Research
Classifier: Programming Language :: Python :: 3
Classifier: Programming Language :: Python :: 3.7
Classifier: Programming Language :: Python :: 3.8
Classifier: Programming Language :: Python :: 3.9
Classifier: Programming Language :: Python :: 3.10
Classifier: Topic :: Software Development :: Libraries
Classifier: Topic :: Software Development :: Libraries :: Python Modules
Requires-Python: >=3.7
License-File: LICENSE
Requires-Dist: numpy
Requires-Dist: torch
Requires-Dist: tqdm
Requires-Dist: more-itertools
Requires-Dist: transformers (>=4.19.0)
Requires-Dist: moviepy (==1.0.3)
Provides-Extra: dev
Requires-Dist: pytest ; extra == 'dev'
